idgenerators/__init__.py
idgenerators/src/__init__.py
idgenerators/src/idgenerators.py
idgenerators/test/__init__.py
idgenerators/test/idgenerators_test.py
idgenerators-1.0.10.dist-info/LICENSE.txt
idgenerators-1.0.10.dist-info/METADATA
idgenerators-1.0.10.dist-info/WHEEL
idgenerators-1.0.10.dist-info/top_level.txt
idgenerators-1.0.10.dist-info/RECORD
