Metadata-Version: 2.1
Name: idgenerators
Version: 1.0.10
Summary: An id generator that generated various types and lengths ids
Home-page: https://github.com/ArjanCodes/2023-package
Author: ArjanCodes
Author-email: arjan@arjancodes.com
License: MIT
Classifier: License :: OSI Approved :: MIT License
Classifier: Programming Language :: Python :: 3.10
Classifier: Operating System :: OS Independent
Requires-Python: >=3.10
License-File: LICENSE.txt
Requires-Dist: bson (>=0.5.10)
Provides-Extra: dev
Requires-Dist: pytest (>=7.0) ; extra == 'dev'
Requires-Dist: twine (>=4.0.2) ; extra == 'dev'
